cheno/__init__.py
cheno/_internal_utils.py
cheno/exceptions.py
cheno/nonparam.py
cheno/param.py
cheno/utils.py
cheno-0.1.3.dist-info/LICENSE
cheno-0.1.3.dist-info/METADATA
cheno-0.1.3.dist-info/WHEEL
cheno-0.1.3.dist-info/top_level.txt
cheno-0.1.3.dist-info/RECORD
