Metadata-Version: 2.1
Name: cheno
Version: 0.1.3
Summary: Forward and Inverse Computation of Null Hypothesis Significance Tests.
Home-page: https://github.com/RCoanda/lib-cheno
Author: Radu-Andrei Coanda
Author-email: radu.coanda@protonmail.com
License: MIT
Platform: UNKNOWN
Requires-Dist: numpy
Requires-Dist: scipy
